{
	"animations": [
		{
			"offsets": [
				-5,
				0
			],
			"loop": false,
			"fps": 24,
			"anim": "idle",
			"indices": [],
			"name": "BF idle dance"
		},
		{
			"offsets": [
				0,
				-5
			],
			"loop": false,
			"fps": 24,
			"anim": "singLEFT",
			"indices": [],
			"name": "BF NOTE LEFT0"
		},
		{
			"offsets": [
				-14,
				-62
			],
			"loop": false,
			"fps": 24,
			"anim": "singDOWN",
			"indices": [],
			"name": "BF NOTE DOWN0"
		},
		{
			"offsets": [
				-1,
				-1
			],
			"loop": false,
			"fps": 24,
			"anim": "singLEFTmiss",
			"indices": [],
			"name": "BF NOTE LEFT MISS"
		},
		{
			"offsets": [
				-16,
				-60
			],
			"loop": false,
			"fps": 24,
			"anim": "singDOWNmiss",
			"indices": [],
			"name": "BF NOTE DOWN MISS"
		},
		{
			"offsets": [
				-36,
				17
			],
			"loop": false,
			"fps": 24,
			"anim": "singUPmiss",
			"indices": [],
			"name": "BF NOTE UP MISS"
		},
		{
			"offsets": [
				-50,
				10
			],
			"loop": false,
			"fps": 24,
			"anim": "singRIGHTmiss",
			"indices": [],
			"name": "BF NOTE RIGHT MISS"
		},
		{
			"loop": false,
			"offsets": [
				0,
				-5
			],
			"anim": "singLEFT-alt",
			"fps": 24,
			"name": "BF ALT LEFT NOTE0",
			"indices": []
		},
		{
			"loop": false,
			"offsets": [
				-45,
				5
			],
			"anim": "singUP-alt",
			"fps": 24,
			"name": "BF ALT NOTE UP0",
			"indices": []
		},
		{
			"loop": false,
			"offsets": [
				-45,
				5
			],
			"anim": "singUP",
			"fps": 24,
			"name": "BF NOTE UP0",
			"indices": []
		},
		{
			"loop": false,
			"offsets": [
				-56,
				-7
			],
			"anim": "singRIGHT-alt",
			"fps": 24,
			"name": "BF ALT NOTE RIGHT0",
			"indices": []
		},
		{
			"loop": false,
			"offsets": [
				-56,
				-7
			],
			"anim": "singRIGHT",
			"fps": 24,
			"name": "BF NOTE RIGHT0",
			"indices": []
		}
	],
	"no_antialiasing": false,
	"image": "characters/bfairship",
	"position": [
		0,
		350
	],
	"healthicon": "bf",
	"flip_x": true,
	"healthbar_colors": [
		49,
		176,
		209
	],
	"camera_position": [
		50,
		-40
	],
	"sing_duration": 4,
	"scale": 1
}